simple_calculator_exl/__init__.py
simple_calculator_exl/core.py
simple_calculator_exl/image_carousel.py
simple_calculator_exl/image_carousel2.py
simple_calculator_exl-0.1.3.dist-info/METADATA
simple_calculator_exl-0.1.3.dist-info/WHEEL
simple_calculator_exl-0.1.3.dist-info/RECORD
